govbr_auth/__init__.py
govbr_auth/controller.py
govbr_auth/utils.py
govbr_auth/__pycache__/__init__.cpython-313.pyc
govbr_auth/core/__init__.py
govbr_auth/core/config.py
govbr_auth/core/govbr.py
govbr_auth/core/__pycache__/__init__.cpython-313.pyc
govbr_auth/core/__pycache__/govbr.cpython-313.pyc
govbr_auth-0.1.4.dist-info/licenses/LICENSE
govbr_auth-0.1.4.dist-info/METADATA
govbr_auth-0.1.4.dist-info/WHEEL
govbr_auth-0.1.4.dist-info/top_level.txt
govbr_auth-0.1.4.dist-info/RECORD
