Metadata-Version: 2.4
Name: govbr-auth
Version: 0.1.4
Summary: Biblioteca de autenticação com o Gov.br para FastAPI, Flask e Django.
Author-email: Joab Leite <leitejoab@gmail.com>
License: MIT
Project-URL: Homepage, https://github.com/cereja-project/govbr_auth
Project-URL: Repository, https://github.com/cereja-project/govbr_auth
Project-URL: Documentation, https://github.com/cereja-project/govbr_auth#readme
Keywords: gov.br,autenticação,fastapi,flask,django
Requires-Python: >=3.8
License-File: LICENSE
Requires-Dist: httpx
Requires-Dist: pyjwt
Requires-Dist: cryptography
Requires-Dist: python-dotenv
Requires-Dist: pydantic
Requires-Dist: cereja
Provides-Extra: fastapi
Requires-Dist: fastapi; extra == "fastapi"
Provides-Extra: flask
Requires-Dist: flask; extra == "flask"
Provides-Extra: django
Requires-Dist: django; extra == "django"
Provides-Extra: full
Requires-Dist: fastapi; extra == "full"
Requires-Dist: flask; extra == "full"
Requires-Dist: django; extra == "full"
Provides-Extra: dev
Requires-Dist: uvicorn; extra == "dev"
Requires-Dist: pytest; extra == "dev"
Requires-Dist: pytest-asyncio; extra == "dev"
Requires-Dist: black; extra == "dev"
Dynamic: license-file
